os_release/__init__.py
os_release/grammar.py
os_release/parser.py
os_release-1.0.1.dist-info/LICENSE
os_release-1.0.1.dist-info/METADATA
os_release-1.0.1.dist-info/WHEEL
os_release-1.0.1.dist-info/top_level.txt
os_release-1.0.1.dist-info/RECORD
