Metadata-Version: 2.1
Name: os-release
Version: 1.0.1
Summary: A module for reading systemd's os-release information on modern Linux distributions.
Home-page: https://github.com/zegelin/py-os-release
Author: Adam Zegelin
Author-email: adam@zegelin.com
License: UNKNOWN
Platform: UNKNOWN
Classifier: Development Status :: 5 - Production/Stable
Classifier: Intended Audience :: Developers
Classifier: License :: OSI Approved :: Apache Software License
Classifier: Topic :: Database
Requires-Dist: arpeggio
Provides-Extra: docs
Requires-Dist: sphinx ; extra == 'docs'
Requires-Dist: sphinx-autodoc-typehints ; extra == 'docs'
Requires-Dist: sphinx-paramlinks ; extra == 'docs'
Requires-Dist: sphinx-rtd-theme ; extra == 'docs'
